decode/__init__.py
decode/auxfuncs.py
decode/hexastring.py
decode/structs.py
decode/wrapper.py
onedecoding-0.0.1.dist-info/LICENSE
onedecoding-0.0.1.dist-info/METADATA
onedecoding-0.0.1.dist-info/WHEEL
onedecoding-0.0.1.dist-info/top_level.txt
onedecoding-0.0.1.dist-info/RECORD
