Metadata-Version: 2.1
Name: onedecoding
Version: 0.0.1
Summary: Libelium One message decode
Home-page: UNKNOWN
Author: Noel Gomariz
Author-email: noel.gomaku@gmail.com
License: UNKNOWN
Keywords: python
Platform: UNKNOWN
Classifier: Development Status :: 1 - Planning
Classifier: Intended Audience :: Developers
Classifier: Programming Language :: Python :: 3
Classifier: Operating System :: Unix
Classifier: Operating System :: MacOS :: MacOS X
Classifier: Operating System :: Microsoft :: Windows
License-File: LICENSE
